{
  "users": [
    {
      "name": "ahmed",
      "id": 81
    },
    {
      "name": "no ",
      "id": 403
    },
    {
      "name": "a ",
      "id": 873
    },
    {
      "name": "hey ",
      "id": 671
    },
    {
      "name": "FootAsso",
      "id": 272
    },
    {
      "name": "Football",
      "id": 838
    },
    {
      "name": "FootAssocaa",
      "id": 417
    },
    {
      "name": "Footbaaaa",
      "id": 999
    },
    {
      "name": "Footbaaaas2oks2s2",
      "id": 744
    },
    {
      "name": "Footbaaaas2oks2s2 ahmed",
      "id": 896
    },
    {
      "name": "FootAssocaake eezzaat",
      "id": 402
    },
    {
      "name": "Footbaaaas2oks2s2 ahmed",
      "id": 248
    },
    {
      "name": "google google google",
      "id": 586
    },
    {
      "name": "google google Football",
      "id": 293
    },
    {
      "name": "google google Football",
      "id": 457
    },
    {
      "name": "google google google",
      "id": 878
    },
    {
      "name": "google",
      "id": 727
    },
    {
      "name": "google",
      "id": 538
    },
    {
      "name": "aaa",
      "id": 721
    },
    {
      "name": "aaa",
      "id": 645
    }
  ]
}